aquarion/libs/libtts/__about__.py
aquarion/libs/libtts/__init__.py
aquarion/libs/libtts/_utils.py
aquarion/libs/libtts/py.typed
aquarion/libs/libtts/api/__init__.py
aquarion/libs/libtts/api/_i18n.py
aquarion/libs/libtts/api/_ttsbackend.py
aquarion/libs/libtts/api/_ttsplugins.py
aquarion/libs/libtts/api/_ttssettings.py
aquarion/libs/libtts/kokoro/__init__.py
aquarion/libs/libtts/kokoro/_backend.py
aquarion/libs/libtts/kokoro/_hook.py
aquarion/libs/libtts/kokoro/_plugin.py
aquarion/libs/libtts/kokoro/settings.py
aquarion/libs/libtts/locale/en/LC_MESSAGES/aquarion-libtts.po
aquarion/libs/libtts/locale/fr/LC_MESSAGES/aquarion-libtts.po
aquarion_libtts-0.1.1.dist-info/METADATA
aquarion_libtts-0.1.1.dist-info/WHEEL
aquarion_libtts-0.1.1.dist-info/entry_points.txt
aquarion_libtts-0.1.1.dist-info/licenses/LICENSES/AGPL-3.0-only.txt
aquarion_libtts-0.1.1.dist-info/RECORD
