Metadata-Version: 2.4
Name: aquarion-libtts
Version: 0.1.1
Summary: Text To Speech (TTS) beckend library for Aquarion AI
Project-URL: Changelog, https://aquarion-libtts.readthedocs.io/en/latest/changelog.html
Project-URL: Documentation, https://aquarion-libtts.readthedocs.io/en/latest/
Project-URL: Homepage, https://github.com/aquarion-ai
Project-URL: Issues, https://github.com/aquarion-ai/aquarion-libtts/issues
Project-URL: Source, https://github.com/aquarion-ai/aquarion-libtts
Author-email: Krys Lawrence <aquarion.5.krystopher@spamgourmet.org>
License-Expression: AGPL-3.0-only
License-File: LICENSES/AGPL-3.0-only.txt
Keywords: ai,aquarion,speech,tts
Classifier: Development Status :: 3 - Alpha
Classifier: Environment :: GPU :: NVIDIA CUDA :: 12
Classifier: Environment :: Plugins
Classifier: Framework :: Hatch
Classifier: Framework :: Pydantic :: 2
Classifier: Framework :: Pytest
Classifier: Framework :: Sphinx
Classifier: Intended Audience :: Developers
Classifier: License :: OSI Approved :: GNU Affero General Public License v3
Classifier: Natural Language :: English
Classifier: Natural Language :: French
Classifier: Operating System :: POSIX :: Linux
Classifier: Programming Language :: Python :: 3.12
Classifier: Programming Language :: Python :: Implementation :: CPython
Classifier: Topic :: Multimedia :: Sound/Audio :: Speech
Classifier: Topic :: Scientific/Engineering :: Artificial Intelligence
Classifier: Topic :: Software Development :: Libraries :: Python Modules
Classifier: Topic :: Text Processing :: Linguistic
Classifier: Typing :: Typed
Requires-Python: >=3.12
Requires-Dist: babel~=2.17.0
Requires-Dist: loguru~=0.7.3
Requires-Dist: pluggy~=1.6.0
Provides-Extra: cpu
Requires-Dist: torch~=2.8.0; extra == 'cpu'
Provides-Extra: cu128
Requires-Dist: torch~=2.8.0; extra == 'cu128'
Provides-Extra: cu129
Requires-Dist: torch~=2.8.0; extra == 'cu129'
Provides-Extra: kokoro
Requires-Dist: kokoro~=0.9.4; extra == 'kokoro'
Requires-Dist: pip~=25.2.0; extra == 'kokoro'
Requires-Dist: pydantic~=2.12.0; extra == 'kokoro'
Requires-Dist: torch~=2.8.0; extra == 'kokoro'
